interpreters_backport/__init__.py
interpreters_backport/metadata.py
interpreters_backport/concurrent/__init__.py
interpreters_backport/concurrent/futures/__init__.py
interpreters_backport/concurrent/futures/interpreter.py
interpreters_backport/concurrent/futures/thread.py
interpreters_backport/interpreters/__init__.py
interpreters_backport/interpreters/_crossinterp.py
interpreters_backport/interpreters/queues.py
interpreters_experimental/__init__.py
interpreters_experimental/interpreters/__init__.py
interpreters_experimental/interpreters/channels.py
interpreters_pep_734-0.5.0.dist-info/LICENSE
interpreters_pep_734-0.5.0.dist-info/METADATA
interpreters_pep_734-0.5.0.dist-info/WHEEL
interpreters_pep_734-0.5.0.dist-info/top_level.txt
interpreters_pep_734-0.5.0.dist-info/RECORD
