Metadata-Version: 2.1
Name: interpreters_pep_734
Version: 0.5.0
Summary: Use this module to try out multiple interpreters and a per-interpreter GIL in Python 3.12+.  Do not use this for anything important yet.
Author-email: Eric Snow <ericsnowcurrently@gmail.com>
Project-URL: Homepage, https://github.com/ericsnowcurrently/interpreters
Project-URL: Bug Tracker, https://github.com/ericsnowcurrently/interpreters/issues
Classifier: Programming Language :: Python :: 3
Classifier: License :: OSI Approved :: BSD License
Classifier: Operating System :: OS Independent
Requires-Python: >=3.12
License-File: LICENSE
